{
	"name": "non",
	"layers": [
		{
			"name": "Layer 0",
			"overriden": 0,
			"subLayers": [],
			"instances": [
				{
					"type": "TiledBackground12",
					"properties": {
						"initially-visible": true,
						"origin": "top-left",
						"wrap-horizontal": "repeat",
						"wrap-vertical": "repeat",
						"image-offset-x": 0,
						"image-offset-y": 0,
						"image-scale-x": 1,
						"image-scale-y": 1,
						"image-angle": 0,
						"enable-tile-randomization": false,
						"x-random": 1,
						"y-random": 1,
						"angle-random": 1,
						"blend-margin-x": 0.1,
						"blend-margin-y": 0.1
					},
					"uid": 983,
					"instanceVariables": {},
					"behaviors": {},
					"world": {
						"x": -244.62201858004028,
						"y": -4.566217238539764,
						"width": 1153.7027063683636,
						"height": 284.53240692160364,
						"originX": 0,
						"originY": 0,
						"color": [
							1,
							1,
							1,
							1
						],
						"angle": 0,
						"zElevation": 0
					}
				},
				{
					"type": "SpriteFont2",
					"properties": {
						"text": "NO DEBERIAS ESTAR AQUI",
						"enable-bbcode": true,
						"character-width": 16,
						"character-height": 16,
						"character-set": "ABCDEFGHIJKLMNOPQRSTUVWXYZabcdefghijklmnopqrstuvwxyz0123456789.,;:?!-_~#\"'&()[]|`\\/@°+=*$£€<>ñÑ←→↑↓%",
						"spacing-data": "",
						"scale": 1,
						"character-spacing": -2,
						"line-height": 0,
						"horizontal-alignment": "center",
						"vertical-alignment": "center",
						"wrapping": "word",
						"initially-visible": true,
						"origin": "top-left",
						"read-aloud": false
					},
					"uid": 1045,
					"instanceVariables": {
						"menu": 1,
						"ID": 0,
						"PLAYER": 0,
						"ox": 64
					},
					"behaviors": {
						"Pin": {
							"properties": {
								"destroy": false
							}
						},
						"Sine": {
							"properties": {
								"movement": "horizontal",
								"wave": "sine",
								"period": 0.1,
								"period-random": 0.2,
								"period-offset": 0,
								"period-offset-random": 0,
								"magnitude": 3,
								"magnitude-random": 0,
								"enabled": false,
								"live-preview": false
							}
						},
						"Tween": {
							"properties": {
								"enabled": true
							}
						}
					},
					"effects": {
						"BetterOutline": {
							"isEnabled": true,
							"parameters": {
								"color": [
									0,
									0,
									0,
									1
								],
								"width": 1,
								"precision-step": 1,
								"samples": 10
							}
						}
					},
					"world": {
						"x": 2.40449693138396,
						"y": -1.8337006197959056,
						"width": 475.35766619296976,
						"height": 270.90713344458584,
						"originX": 0,
						"originY": 0,
						"color": [
							1,
							1,
							1,
							1
						],
						"angle": 0,
						"zElevation": 0
					}
				}
			],
			"sid": 179715996064999,
			"effectTypes": [],
			"isInitiallyVisible": true,
			"isInitiallyInteractive": true,
			"isHTMLElementsLayer": false,
			"color": [
				1,
				1,
				1,
				1
			],
			"backgroundColor": [
				0,
				0,
				0,
				1
			],
			"isTransparent": false,
			"parallaxX": 1,
			"parallaxY": 1,
			"scaleRate": 1,
			"forceOwnTexture": false,
			"renderingMode": "3d",
			"drawOrder": "z-order",
			"useRenderCells": false,
			"blendMode": "normal",
			"zElevation": 0,
			"global": false
		}
	],
	"sid": 889144027810475,
	"nonworld-instances": [],
	"effectTypes": [],
	"width": 960,
	"height": 540,
	"unboundedScrolling": false,
	"vpX": 0.5,
	"vpY": 0.5,
	"projection": "perspective",
	"eventSheet": "Event sheet 4"
}