{
	"name": "Plane",
	"plugin-id": "Sprite",
	"sid": 284538365103756,
	"isGlobal": false,
	"instanceVariables": [],
	"behaviorTypes": [
		{
			"behaviorId": "solid",
			"name": "Solid",
			"sid": 669433878943659
		}
	],
	"effectTypes": [],
	"animations": {
		"items": [
			{
				"frames": [
					{
						"width": 352,
						"height": 194,
						"originX": 0.5,
						"originY": 0.5,
						"originalSource": "",
						"exportFormat": "lossless",
						"exportQuality": 0.8,
						"imageSpriteId": 8460729,
						"collisionPoly": {
							"points": [
								0.06534090909090909,
								0.21649484536082475,
								0.11079545454545454,
								0.21649484536082475,
								0.2180397781458768,
								0.44974228770462504,
								0.3156960227272727,
								0.5135309524142861,
								0.823153409090909,
								0.5135309229192044,
								0.8863636363636364,
								0.5670103092783505,
								0.9318181818181818,
								0.6597938144329897,
								0.8636363636363636,
								0.7268041237113402,
								0.5738636363636364,
								0.7422680412371134,
								0.29545454545454547,
								0.6907216494845361,
								0.17045454545454544,
								0.634020618556701,
								0.08806818181818182,
								0.5824742268041238,
								0.04261363636363636,
								0.5,
								0.10298295183615258,
								0.5083762837439465
							]
						},
						"useCollisionPoly": true,
						"duration": 1,
						"tag": ""
					}
				],
				"sid": 208709836707346,
				"name": "Animation 1",
				"isLooping": false,
				"isPingPong": false,
				"repeatCount": 1,
				"repeatTo": 0,
				"speed": 5
			}
		],
		"subfolders": []
	}
}